strands_teams/__init__.py
strands_teams/teams.py
strands_teams/templates/__init__.py
strands_teams/templates/teams_templates.py
strands_teams-0.1.0.dist-info/licenses/LICENSE
strands_teams-0.1.0.dist-info/METADATA
strands_teams-0.1.0.dist-info/WHEEL
strands_teams-0.1.0.dist-info/top_level.txt
strands_teams-0.1.0.dist-info/RECORD
